antioch/__init__.py
antioch/clock.py
antioch/execution.py
antioch/input.py
antioch/module.py
antioch/node.py
antioch_py-3.0.12.dist-info/licenses/LICENSE
common/__init__.py
common/constants.py
common/ark/__init__.py
common/ark/ark.py
common/ark/hardware.py
common/ark/kinematics.py
common/ark/module.py
common/ark/node.py
common/ark/scheduler.py
common/ark/sim.py
common/ark/token.py
common/assets/__init__.py
common/assets/rigging.usd
common/core/__init__.py
common/core/auth.py
common/core/container.py
common/core/registry.py
common/core/rome.py
common/core/telemetry.py
common/core/types.py
common/message/__init__.py
common/message/annotation.py
common/message/array.py
common/message/camera.py
common/message/color.py
common/message/detection.py
common/message/foxglove.py
common/message/frame.py
common/message/image.py
common/message/imu.py
common/message/joint.py
common/message/log.py
common/message/message.py
common/message/pir.py
common/message/plot.py
common/message/point.py
common/message/point_cloud.py
common/message/pose.py
common/message/quaternion.py
common/message/radar.py
common/message/twist.py
common/message/types.py
common/message/vector.py
common/sim/__init__.py
common/sim/objects.py
common/sim/state.py
common/utils/__init__.py
common/utils/comms.py
common/utils/logger.py
common/utils/time.py
antioch_py-3.0.12.dist-info/METADATA
antioch_py-3.0.12.dist-info/WHEEL
antioch_py-3.0.12.dist-info/top_level.txt
antioch_py-3.0.12.dist-info/RECORD
