Metadata-Version: 2.4
Name: antioch-py
Version: 3.0.12
Summary: Antioch Python Module SDK
Author-email: Antioch Robotics <support@antioch.dev>
License-Expression: MIT
Project-URL: Homepage, https://antioch.com
Keywords: robotics,simulation,middleware,sdk,modules
Classifier: Development Status :: 4 - Beta
Classifier: Intended Audience :: Developers
Classifier: Programming Language :: Python :: 3
Classifier: Programming Language :: Python :: 3.12
Classifier: Topic :: Scientific/Engineering :: Artificial Intelligence
Classifier: Topic :: Software Development :: Libraries :: Python Modules
Requires-Python: <3.13,>=3.10
License-File: LICENSE
Requires-Dist: click>=8.0.0
Requires-Dist: docker>=7.0.0
Requires-Dist: eclipse-zenoh>=1.5.0
Requires-Dist: foxglove-sdk>=0.14.1
Requires-Dist: httpx>=0.27.0
Requires-Dist: loguru>=0.7.3
Requires-Dist: msgpack==1.1.1
Requires-Dist: msgpack>=1.1.1
Requires-Dist: numpy==1.26.0
Requires-Dist: ormsgpack>=1.6.0
Requires-Dist: pydantic>=2.11.6
Requires-Dist: pydantic>=2.11.7
Requires-Dist: pyyaml>=6.0.2
Requires-Dist: scipy==1.15.3
Requires-Dist: sortedcontainers-stubs>=2.4.3
Requires-Dist: sortedcontainers>=2.4.0
Dynamic: license-file
